hotel/__init__.py
hotel/principal.py
hotel/bbdd/reservas.sql
hotel/bbdd/reservas.sqlite
hotel/img/imagen_menu.png
hotel/modelos/__init__.py
hotel/modelos/datos.py
hotel/ui/frmlogin.ui
hotel/ui/frmmenu.ui
hotel/ui/frmmostrarreservas.ui
hotel/ui/frmreservar.ui
hotel/vistas/__init__.py
hotel/vistas/vlogin.py
hotel/vistas/vmenu.py
hotel/vistas/vmostrarreservas.py
hotel/vistas/vreservar.py
hotel_tatianlara-1.0.0.dist-info/METADATA
hotel_tatianlara-1.0.0.dist-info/WHEEL
hotel_tatianlara-1.0.0.dist-info/entry_points.txt
hotel_tatianlara-1.0.0.dist-info/top_level.txt
hotel_tatianlara-1.0.0.dist-info/RECORD
