Metadata-Version: 2.4
Name: hotel-tatianlara
Version: 1.0.0
Summary: Aplicación realizada para la Tarea 3
Author: Tatiana Lara Redondo
Requires-Dist: PyQt5
Dynamic: author
Dynamic: requires-dist
Dynamic: summary
